{"data":{"appClassicJson":{"keyFeatures":{"slogan":"WHATS THE FUNCTION","title":"Meet the feature of app","features":[{"id":1,"color":"#F55767","icon":{"publicURL":"/static/keyFeature-1-9ac0d08e74fe7f7dd73acdddb02f995b.svg"},"title":"Fast Performance","description":"Get your blood tests delivered at home collect a sample from the news your blood tests."},{"id":2,"color":"#2563FF","icon":{"publicURL":"/static/keyFeature-2-36ca3ce752bee720d5808817de83ac6f.svg"},"title":"Prototyping","description":"Get your blood tests delivered at home collect a sample from the news your blood tests."},{"id":3,"color":"#40975F","icon":{"publicURL":"/static/keyFeature-3-c355accc8e11e47b0686b7e1fe3013f8.svg"},"title":"Vector Editing","description":"Get your blood tests delivered at home collect a sample from the news your blood tests."}]}}}}